{
  "$id": "https://open-metadata.org/schema/entity/data/database.json",
  "$schema": "http://json-schema.org/draft-07/schema#",
  "title": "Database",
  "description": "This schema defines the Database entity. A database also referred to as Database Catalog is a collection of tables.",
  "type": "object",

  "definitions": {
    "databaseName": {
      "description": "Name that identifies the database.",
      "type": "string",
      "minLength": 1,
      "maxLength": 128,
      "pattern": "^[^.]*$"
    }
  },
  "properties": {
    "id": {
      "description": "Unique identifier that identifies this database instance.",
      "$ref": "../../type/basic.json#/definitions/uuid"
    },
    "name": {
      "description": "Name that identifies the database.",
      "$ref": "#/definitions/databaseName"
    },
    "fullyQualifiedName": {
      "description": "Name that uniquely identifies a database in the format 'ServiceName.DatabaseName'.",
      "type": "string"
    },
    "displayName": {
      "description": "Display Name that identifies this database.",
      "type": "string"
    },
    "description": {
      "description": "Description of the database instance.",
      "type": "string"
    },
    "version": {
      "description": "Metadata version of the entity.",
      "$ref": "../../type/entityHistory.json#/definitions/entityVersion"
    },
    "updatedAt": {
      "description": "Last update time corresponding to the new version of the entity in Unix epoch time milliseconds.",
      "$ref": "../../type/basic.json#/definitions/timestamp"
    },
    "updatedBy": {
      "description": "User who made the update.",
      "type": "string"
    },
    "href": {
      "description": "Link to the resource corresponding to this entity.",
      "$ref": "../../type/basic.json#/definitions/href"
    },
    "owner": {
      "description": "Owner of this database.",
      "$ref": "../../type/entityReference.json"
    },
    "service": {
      "description": "Link to the database cluster/service where this database is hosted in.",
      "$ref": "../../type/entityReference.json"
    },
    "serviceType": {
      "description": "Service type where this database is hosted in.",
      "$ref": "../services/databaseService.json#/definitions/databaseServiceType"
    },
    "location": {
      "description": "Reference to the Location that contains this database.",
      "$ref": "../../type/entityReference.json"
    },
    "usageSummary": {
      "description": "Latest usage information for this database.",
      "$ref": "../../type/usageDetails.json",
      "default": null
    },
    "tables": {
      "description": "References to tables in the database.",
      "$ref": "../../type/entityReference.json#/definitions/entityReferenceList"
    },
    "changeDescription": {
      "description": "Change that lead to this version of the entity.",
      "$ref": "../../type/entityHistory.json#/definitions/changeDescription"
    },
    "deleted": {
      "description": "When `true` indicates the entity has been soft deleted.",
      "type": "boolean",
      "default": false
    }
  },
  "required": ["name", "service"],
  "additionalProperties": false
}
