{
  "entity" : "dashboard_data_model",
  "extends" : "entity_base",
  "settings" : {
    "byLanguage" : {
      "en" : { },
      "jp" : {
        "index" : {
          "max_ngram_diff" : 17
        }
      },
      "ru" : { },
      "zh" : {
        "index" : {
          "max_ngram_diff" : 17
        },
        "analysis" : {
          "tokenizer" : {
            "n_gram_tokenizer" : {
              "min_gram" : 1,
              "max_gram" : 2
            }
          }
        }
      }
    }
  },
  "fields" : {
    "name" : {
      "languages" : {
        "zh" : {
          "search_analyzer" : "ik_smart"
        }
      }
    },
    "displayName" : {
      "type" : "text_search_full",
      "languages" : {
        "zh" : {
          "search_analyzer" : "ik_smart"
        }
      }
    },
    "description" : {
      "languages" : {
        "jp" : {
          "term_vector" : null
        },
        "zh" : {
          "search_analyzer" : "ik_smart",
          "term_vector" : null
        }
      }
    },
    "dataProducts" : {
      "overrides" : {
        "properties" : {
          "name" : {
            "normalizer" : "lowercase_normalizer",
            "fields" : {
              "keyword" : {
                "normalizer" : null
              }
            }
          }
        }
      },
      "languages" : {
        "ru" : {
          "properties" : {
            "displayName" : {
              "fields" : {
                "keyword" : {
                  "normalizer" : null
                }
              }
            }
          }
        }
      }
    },
    "sourceUrl" : {
      "type" : "keyword"
    },
    "owners" : {
      "overrides" : {
        "type" : "nested",
        "properties" : {
          "name" : {
            "fields" : {
              "keyword" : {
                "normalizer" : null
              }
            }
          },
          "fullyQualifiedName" : {
            "type" : "text"
          }
        }
      }
    },
    "tier" : {
      "languages" : {
        "jp" : {
          "properties" : {
            "tagFQN" : {
              "fields" : {
                "text" : {
                  "analyzer" : "om_analyzer"
                }
              },
              "normalizer" : null
            }
          }
        },
        "ru" : {
          "properties" : {
            "tagFQN" : {
              "normalizer" : null
            }
          }
        },
        "zh" : {
          "properties" : {
            "tagFQN" : {
              "fields" : {
                "text" : {
                  "analyzer" : "om_analyzer"
                }
              },
              "normalizer" : null
            }
          }
        }
      }
    },
    "tags" : {
      "overrides" : {
        "properties" : {
          "tagFQN" : {
            "fields" : null
          }
        }
      },
      "languages" : {
        "jp" : {
          "properties" : {
            "tagFQN" : {
              "fields" : {
                "text" : {
                  "type" : "text",
                  "analyzer" : "om_analyzer"
                }
              }
            }
          }
        },
        "zh" : {
          "properties" : {
            "tagFQN" : {
              "fields" : {
                "text" : {
                  "type" : "text",
                  "analyzer" : "om_analyzer"
                }
              }
            }
          }
        }
      }
    },
    "service" : {
      "overrides" : {
        "properties" : {
          "fullyQualifiedName" : {
            "type" : "text",
            "fields" : {
              "keyword" : {
                "type" : "keyword",
                "normalizer" : "lowercase_normalizer",
                "ignore_above" : 256
              }
            }
          }
        }
      }
    },
    "upstreamLineage" : {
      "fragment" : "upstreamLineage",
      "list" : true
    },
    "dataModelType" : {
      "type" : "keyword_lc",
      "languages" : {
        "jp" : {
          "normalizer" : null
        },
        "zh" : {
          "normalizer" : null
        }
      }
    },
    "columns" : {
      "fragment" : "columns",
      "overrides" : {
        "properties" : {
          "name" : {
            "type" : "keyword",
            "fields" : {
              "ngram" : null
            },
            "analyzer" : null
          },
          "description" : {
            "similarity" : null
          },
          "fullyQualifiedName" : {
            "type" : "text",
            "normalizer" : null
          },
          "tags" : {
            "properties" : {
              "tagFQN" : {
                "fields" : null
              },
              "description" : {
                "similarity" : null
              }
            }
          },
          "fqnParts" : null
        }
      },
      "list" : true,
      "languages" : {
        "jp" : {
          "properties" : {
            "description" : {
              "index_options" : "docs",
              "norms" : false,
              "term_vector" : null
            },
            "extension" : null,
            "customPropertiesTyped" : null
          }
        },
        "ru" : {
          "properties" : {
            "extension" : null,
            "customPropertiesTyped" : null
          }
        },
        "zh" : {
          "properties" : {
            "description" : {
              "index_options" : "docs",
              "search_analyzer" : "ik_smart",
              "norms" : false,
              "term_vector" : null
            },
            "extension" : null,
            "customPropertiesTyped" : null
          }
        }
      }
    },
    "columnNames" : {
      "type" : "keyword",
      "list" : true
    },
    "project" : {
      "inline" : {
        "type" : "text",
        "fields" : {
          "keyword" : {
            "type" : "keyword",
            "normalizer" : "lowercase_normalizer",
            "ignore_above" : 256
          }
        }
      },
      "languages" : {
        "jp" : {
          "fields" : {
            "keyword" : {
              "normalizer" : null
            }
          }
        },
        "zh" : {
          "fields" : {
            "actualCase" : {
              "type" : "keyword",
              "ignore_above" : 256
            },
            "ngram" : {
              "type" : "text",
              "analyzer" : "om_ngram"
            }
          }
        }
      }
    },
    "lifeCycle" : {
      "type" : "object_no_dynamic"
    },
    "domains" : {
      "overrides" : {
        "properties" : {
          "name" : {
            "fields" : {
              "keyword" : {
                "normalizer" : null
              }
            }
          }
        }
      }
    },
    "extension" : {
      "type" : "flattened",
      "languages" : {
        "jp" : null,
        "zh" : null
      }
    },
    "descriptionSources" : {
      "type" : "object_no_dynamic",
      "languages" : {
        "jp" : null,
        "zh" : null
      }
    },
    "tagSources" : {
      "type" : "object_no_dynamic",
      "languages" : {
        "jp" : null,
        "zh" : null
      }
    },
    "tierSources" : {
      "type" : "object_no_dynamic",
      "languages" : {
        "jp" : null,
        "zh" : null
      }
    },
    "certification" : {
      "languages" : {
        "jp" : {
          "properties" : {
            "tagLabel" : {
              "properties" : {
                "tagFQN" : {
                  "fields" : {
                    "text" : {
                      "analyzer" : "om_analyzer"
                    }
                  }
                }
              }
            }
          }
        },
        "zh" : {
          "properties" : {
            "tagLabel" : {
              "properties" : {
                "tagFQN" : {
                  "fields" : {
                    "text" : {
                      "analyzer" : "om_analyzer"
                    }
                  }
                }
              }
            }
          }
        }
      }
    },
    "fqnHash" : {
      "type" : "fqn_hash"
    },
    "customPropertiesTyped" : {
      "fragment" : "customPropertiesTyped",
      "list" : true,
      "languages" : {
        "jp" : {
          "properties" : {
            "textValue" : {
              "analyzer" : "om_analyzer"
            }
          }
        },
        "zh" : {
          "properties" : {
            "textValue" : {
              "analyzer" : "om_analyzer"
            }
          }
        }
      }
    },
    "fingerprint" : {
      "type" : "keyword"
    },
    "textToLLMContext" : {
      "type" : "text"
    },
    "textToEmbed" : {
      "type" : "text"
    },
    "chunkIndex" : {
      "type" : "integer"
    },
    "chunkCount" : {
      "type" : "integer"
    },
    "parentId" : {
      "type" : "keyword"
    },
    "lineageSqlQueries" : {
      "type" : "object_disabled"
    },
    "votes" : {
      "inline" : {
        "dynamic" : false,
        "properties" : {
          "upVotes" : {
            "type" : "integer"
          },
          "downVotes" : {
            "type" : "integer"
          }
        }
      },
      "languages" : {
        "en" : null,
        "ru" : null,
        "zh" : null
      }
    }
  }
}
